bead_inspector/.coverage
bead_inspector/__init__.py
bead_inspector/_version.py
bead_inspector/constants.py
bead_inspector/file_utils.py
bead_inspector/main.py
bead_inspector/reporting.py
bead_inspector/rules.py
bead_inspector/validator.py
bead_inspector-0.1.2.post15.dist-info/LICENSE
bead_inspector-0.1.2.post15.dist-info/METADATA
bead_inspector-0.1.2.post15.dist-info/WHEEL
bead_inspector-0.1.2.post15.dist-info/entry_points.txt
bead_inspector-0.1.2.post15.dist-info/top_level.txt
bead_inspector-0.1.2.post15.dist-info/RECORD
