Metadata-Version: 2.1
Name: bead_inspector
Version: 0.1.2.post15
Summary: A tool to help SBOs validate BEAD Challenge Process data files before submission to NTIA.
Author-email: Matt Triano <matthewtriano@uchicago.edu>, Nick Ross <tspread@uchicago.edu>
Maintainer: Matt Triano, Nick Ross
Project-URL: Homepage, https://github.com/uchicago-dsi/uchicago-bead-challenge-validation-tool
Project-URL: Issues, https://github.com/uchicago-dsi/uchicago-bead-challenge-validation-tool/issues
Classifier: Programming Language :: Python :: 3
Classifier: Operating System :: OS Independent
Requires-Python: >=3.7
License-File: LICENSE
Provides-Extra: dev
Requires-Dist: flake8 ; extra == 'dev'
Requires-Dist: twine ; extra == 'dev'
Requires-Dist: tox >=4.0 ; extra == 'dev'
Requires-Dist: black ; extra == 'dev'
Requires-Dist: isort ; extra == 'dev'
Requires-Dist: pytest >=6.0 ; extra == 'dev'
Requires-Dist: pytest-cov ; extra == 'dev'
Requires-Dist: ruff ; extra == 'dev'
